enhancer/__init__.py
enhancer/enhancer.py
enhancer/utils.py
image_enhancer_vivi-0.1.2.dist-info/METADATA
image_enhancer_vivi-0.1.2.dist-info/WHEEL
image_enhancer_vivi-0.1.2.dist-info/top_level.txt
image_enhancer_vivi-0.1.2.dist-info/RECORD
